{
  "code": "cart",
  "class": "vintagerails.SeatSup",
  "hitboxSize": {
    "x": 1,
    "y": 1
  },
  "drops": [],
  "behaviorConfigs": {
    "rideableaccessories": {
        "wearableSlots": [
        {
          "code": "Seat",
          "forCategoryCodes": ["basket"],
          "attachmentPointCode": "SeatAP",
          "emptyInteractPassThrough": true,
          "stepParentTo": {
            "": { "elementName": "Seat" }
          }
        }
      ]
    },
    "creaturecarrier": {
      "seats": [
        {
          "apName": "SeatAP",
          "controllable": false
        }
      ]
    },
    "selectionboxes" : {
      "selectionboxes": [
        "SeatAP"
      ]
    }
  },
  "client": {
    "renderer": "vintagerails.ShapeFixedRot",
    "shape": {
      "base": "vintagerails:entity/carts/minecart"
    },
    "behaviors": [
      { "code": "interpolateposition" },
      { "code": "selectionboxes" },
      { "code": "rideableaccessories" },
      { "code": "creaturecarrier" }
    ]
  },
  "server": {
    "behaviors": [
      { "code": "vintagerails.TrackRider" },
      { "code": "passivephysics" },
      { "code": "selectionboxes" },
      { "code": "rideableaccessories" },
      { "code": "creaturecarrier" }
    ]
  }
}
